exp4/__init__.py
exp4/algo.py
exp4-0.1.4.dist-info/LICENSE
exp4-0.1.4.dist-info/WHEEL
exp4-0.1.4.dist-info/METADATA
exp4-0.1.4.dist-info/RECORD
